pixiedust_node/__init__.py
pixiedust_node/node.py
pixiedust_node/nodestdreader.py
pixiedust_node/npm.py
pixiedust_node/package.json
pixiedust_node/pixiedustNodeRepl.js
pixiedust_node-0.1.2.dist-info/DESCRIPTION.rst
pixiedust_node-0.1.2.dist-info/METADATA
pixiedust_node-0.1.2.dist-info/RECORD
pixiedust_node-0.1.2.dist-info/WHEEL
pixiedust_node-0.1.2.dist-info/metadata.json
pixiedust_node-0.1.2.dist-info/top_level.txt
